pytools/__init__.py
pytools/batchjob.py
pytools/codegen.py
pytools/convergence.py
pytools/datatable.py
pytools/debug.py
pytools/graph.py
pytools/graphviz.py
pytools/lex.py
pytools/mpi.py
pytools/mpiwrap.py
pytools/obj_array.py
pytools/persistent_dict.py
pytools/prefork.py
pytools/py.typed
pytools/py_codegen.py
pytools/spatial_btree.py
pytools/stopwatch.py
pytools/tag.py
pytools/version.py
pytools/test/__init__.py
pytools/test/test_data_table.py
pytools/test/test_dataclasses.py
pytools/test/test_graph_tools.py
pytools/test/test_math_stuff.py
pytools/test/test_mpi.py
pytools/test/test_persistent_dict.py
pytools/test/test_py_codegen.py
pytools/test/test_pytools.py
pytools-2025.2.4.dist-info/METADATA
pytools-2025.2.4.dist-info/WHEEL
pytools-2025.2.4.dist-info/licenses/LICENSE
pytools-2025.2.4.dist-info/RECORD
