Metadata-Version: 2.4
Name: pytools
Version: 2025.2.4
Summary: A collection of tools for Python
Project-URL: Documentation, https://documen.tician.de/pytools/
Project-URL: Homepage, https://github.com/inducer/pytools/
Author-email: Andreas Kloeckner <inform@tiker.net>
License-Expression: MIT
License-File: LICENSE
Classifier: Development Status :: 4 - Beta
Classifier: Intended Audience :: Developers
Classifier: Intended Audience :: Other Audience
Classifier: Intended Audience :: Science/Research
Classifier: Natural Language :: English
Classifier: Programming Language :: Python
Classifier: Programming Language :: Python :: 3 :: Only
Classifier: Topic :: Scientific/Engineering
Classifier: Topic :: Scientific/Engineering :: Information Analysis
Classifier: Topic :: Scientific/Engineering :: Mathematics
Classifier: Topic :: Scientific/Engineering :: Visualization
Classifier: Topic :: Software Development :: Libraries
Classifier: Topic :: Utilities
Requires-Python: >=3.10
Requires-Dist: platformdirs>=2.2
Requires-Dist: siphash24>=1.6
Requires-Dist: typing-extensions>=4.5
Provides-Extra: numpy
Requires-Dist: numpy>=1.6; extra == 'numpy'
Provides-Extra: test
Requires-Dist: basedpyright; extra == 'test'
Requires-Dist: pytest; extra == 'test'
Requires-Dist: ruff; extra == 'test'
